esm_archiving/__init__.py
esm_archiving/cli.py
esm_archiving/config.py
esm_archiving/esm_archiving.py
esm_archiving/external/__init__.py
esm_archiving/external/pypftp.py
esm_calendar/__init__.py
esm_calendar/esm_calendar.py
esm_cleanup/__init__.py
esm_cleanup/cli.py
esm_cleanup/esm_cleanup.py
esm_database/__init__.py
esm_database/cli.py
esm_database/esm_database.py
esm_database/getch.py
esm_database/location_database.py
esm_environment/__init__.py
esm_environment/esm_environment.py
esm_master/__init__.py
esm_master/cli.py
esm_master/compile_info.py
esm_master/database.py
esm_master/database_actions.py
esm_master/esm_master.py
esm_master/general_stuff.py
esm_master/software_package.py
esm_master/task.py
esm_motd/__init__.py
esm_motd/esm_motd.py
esm_parser/__init__.py
esm_parser/dict_to_yaml.py
esm_parser/esm_parser.py
esm_parser/provenance.py
esm_parser/yaml_to_dict.py
esm_plugin_manager/__init__.py
esm_plugin_manager/cli.py
esm_plugin_manager/esm_plugin_manager.py
esm_profile/__init__.py
esm_profile/esm_profile.py
esm_runscripts/__init__.py
esm_runscripts/assembler.py
esm_runscripts/batch_system.py
esm_runscripts/chunky_parts.py
esm_runscripts/cli.py
esm_runscripts/compute.py
esm_runscripts/config_initialization.py
esm_runscripts/coupler.py
esm_runscripts/database.py
esm_runscripts/database_actions.py
esm_runscripts/dataprocess.py
esm_runscripts/event_handlers.py
esm_runscripts/filelists.py
esm_runscripts/helpers.py
esm_runscripts/inspect.py
esm_runscripts/jinja.py
esm_runscripts/last_minute.py
esm_runscripts/logfiles.py
esm_runscripts/methods.py
esm_runscripts/mpirun.py
esm_runscripts/namelists.py
esm_runscripts/oasis.py
esm_runscripts/observe.py
esm_runscripts/pbs.py
esm_runscripts/postprocess.py
esm_runscripts/prepare.py
esm_runscripts/prepcompute.py
esm_runscripts/prepexp.py
esm_runscripts/prev_run.py
esm_runscripts/resubmit.py
esm_runscripts/sim_objects.py
esm_runscripts/slurm.py
esm_runscripts/tidy.py
esm_runscripts/virtual_env_builder.py
esm_tools-6.54.3.dist-info/LICENSE
esm_tools-6.54.3.dist-info/METADATA
esm_tools-6.54.3.dist-info/WHEEL
esm_tools-6.54.3.dist-info/entry_points.txt
esm_tools-6.54.3.dist-info/top_level.txt
esm_tools-6.54.3.dist-info/RECORD
