Metadata-Version: 2.1
Name: esm-tools
Version: 6.54.3
Summary: ESM Tools external infrastructure for Earth System Modelling
Home-page: https://github.com/esm-tools/esm_tools
Author: The ESM Tools Team
Author-email: ['dirk.barbi@awi.de', 'paul.gierz@awi.de', 'miguel.andres-martinez@awi.de', 'deniz.ural@awi.de', 'jan.streffing@awi.de', 'sebastian.wahl@geomar.de', 'kai.himstedt@dkrz.de']
License: GNU General Public License v2
Keywords: esm_tools
Classifier: Development Status :: 3 - Alpha
Classifier: Intended Audience :: Science/Research
Classifier: License :: OSI Approved :: GNU General Public License v2 (GPLv2)
Classifier: Natural Language :: English
Classifier: Programming Language :: Python :: 3
Classifier: Programming Language :: Python :: 3.6
Classifier: Programming Language :: Python :: 3.7
Classifier: Programming Language :: Python :: 3.8
Classifier: Programming Language :: Python :: 3.9
Classifier: Programming Language :: Python :: 3.10
Classifier: Programming Language :: Python :: 3.11
Requires-Python: >=3.6, <3.12
License-File: LICENSE
Requires-Dist: Click >=8.0.4
Requires-Dist: PyGithub ==1.55
Requires-Dist: colorama ==0.4.5
Requires-Dist: coloredlogs ==15.0.1
Requires-Dist: emoji ==1.7.0
Requires-Dist: f90nml ==1.4.2
Requires-Dist: gfw-creator ==0.2.2
Requires-Dist: gitpython ==3.1.41
Requires-Dist: h5netcdf >=0.8.1
Requires-Dist: jinja2 ==3.1.6
Requires-Dist: loguru ==0.6.0
Requires-Dist: numpy >=1.19.5
Requires-Dist: packaging ==21.3
Requires-Dist: pandas >=1.1.5
Requires-Dist: psutil ==5.9.1
Requires-Dist: pydantic >=1.10.13
Requires-Dist: pytest ==7.1.2
Requires-Dist: pyyaml ==6.0.1
Requires-Dist: questionary ==1.10.0
Requires-Dist: ruamel.yaml ==0.17.32
Requires-Dist: semver ==2.13.0
Requires-Dist: sqlalchemy >=1.4.39
Requires-Dist: tabulate ==0.8.10
Requires-Dist: tqdm ==4.66.3
Requires-Dist: typing-extensions >=4.1.1
Requires-Dist: xdgenvpy ==2.3.5
